{
    "logs": [
        {
            "outputFile": "C:\\Users\\DELL\\AndroidStudioProjects\\Postie11\\app\\build\\intermediates\\incremental\\mergeDebugResources\\merged.dir\\values\\values.xml",
            "map": [
                {
                    "source": "C:\\Users\\DELL\\.gradle\\caches\\transforms-2\\files-2.1\\fc9a8d5df99331dac9a5fdc49a7080c6\\play-services-base-17.1.0\\res\\values\\values.xml",
                    "from": {
                        "startLines": "4,5,6,7,8,9,10,11,14,15,16,17,18,19,20,21,22,23,24,25,26,27,28,29,30,33,46",
                        "startColumns": "0,0,0,0,0,0,0,0,0,0,0,0,0,0,0,0,0,0,0,0,0,0,0,0,0,0,0",
                        "startOffsets": "215,301,377,463,549,625,702,778,951,1052,1233,1354,1457,1637,1756,1868,1967,2155,2256,2437,2558,2733,2877,2936,2994,3164,3475",
                        "endLines": "4,5,6,7,8,9,10,11,14,15,16,17,18,19,20,21,22,23,24,25,26,27,28,29,30,45,64",
                        "endColumns": "85,75,85,85,75,76,75,75,100,180,120,102,179,118,111,98,187,100,180,120,174,143,58,57,74,20,20",
                        "endOffsets": "300,376,462,548,624,701,777,853,1051,1232,1353,1456,1636,1755,1867,1966,2154,2255,2436,2557,2732,2876,2935,2993,3068,3474,3887"
                    },
                    "to": {
                        "startLines": "196,197,198,199,200,201,202,203,624,625,626,627,628,629,630,631,633,634,635,636,637,638,639,640,641,4215,4505",
                        "startColumns": "4,4,4,4,4,4,4,4,4,4,4,4,4,4,4,4,4,4,4,4,4,4,4,4,4,4,4",
                        "startOffsets": "10173,10263,10343,10433,10523,10603,10684,10764,37847,37952,38133,38258,38365,38545,38668,38784,39054,39242,39347,39528,39653,39828,39976,40039,40101,272277,288561",
                        "endLines": "196,197,198,199,200,201,202,203,624,625,626,627,628,629,630,631,633,634,635,636,637,638,639,640,641,4227,4523",
                        "endColumns": "89,79,89,89,79,80,79,79,104,180,124,106,179,122,115,102,187,104,180,124,174,147,62,61,78,20,20",
                        "endOffsets": "10258,10338,10428,10518,10598,10679,10759,10839,37947,38128,38253,38360,38540,38663,38779,38882,39237,39342,39523,39648,39823,39971,40034,40096,40175,272587,288973"
                    }
                },
                {
                    "source": "C:\\Users\\DELL\\.gradle\\caches\\transforms-2\\files-2.1\\14e1904a47c75ffdbd7bc4595a7ccff8\\glide-4.11.0\\res\\values\\values.xml",
                    "from": {
                        "startLines": "2",
                        "startColumns": "4",
                        "startOffsets": "55",
                        "endColumns": "57",
                        "endOffsets": "108"
                    },
                    "to": {
                        "startLines": "527",
                        "startColumns": "4",
                        "startOffsets": "31749",
                        "endColumns": "57",
                        "endOffsets": "31802"
                    }
                },
                {
                    "source": "C:\\Users\\DELL\\.gradle\\caches\\transforms-2\\files-2.1\\967dd6e0da3aec512e9538eb43b29c1c\\android-image-cropper-2.8.0\\res\\values\\values.xml",
                    "from": {
                        "startLines": "48,49,50,51,52,53,54,55,56,2",
                        "startColumns": "4,4,4,4,4,4,4,4,4,4",
                        "startOffsets": "2475,2587,2634,2688,2742,2822,2898,2979,3043,55",
                        "endLines": "48,49,50,51,52,53,54,55,56,47",
                        "endColumns": "111,46,53,53,79,75,80,63,73,24",
                        "endOffsets": "2582,2629,2683,2737,2817,2893,2974,3038,3112,2470"
                    },
                    "to": {
                        "startLines": "642,643,644,645,646,647,648,649,667,3971",
                        "startColumns": "4,4,4,4,4,4,4,4,4,4",
                        "startOffsets": "40180,40292,40339,40393,40447,40527,40603,40684,42930,257649",
                        "endLines": "642,643,644,645,646,647,648,649,667,4016",
                        "endColumns": "111,46,53,53,79,75,80,63,73,24",
                        "endOffsets": "40287,40334,40388,40442,40522,40598,40679,40743,42999,260064"
                    }
                },
                {
                    "source": "C:\\Users\\DELL\\.gradle\\caches\\transforms-2\\files-2.1\\4912a732fa4051a3f165a3a135002b21\\transition-1.0.0\\res\\values\\values.xml",
                    "from": {
                        "startLines": "2,3,4,5,6,7,8,9,10,11",
                        "startColumns": "4,4,4,4,4,4,4,4,4,4",
                        "startOffsets": "55,95,138,185,240,285,339,391,440,501",
                        "endColumns": "39,42,46,54,44,53,51,48,60,49",
                        "endOffsets": "90,133,180,235,280,334,386,435,496,546"
                    },
                    "to": {
                        "startLines": "526,534,537,538,539,557,558,559,560,561",
                        "startColumns": "4,4,4,4,4,4,4,4,4,4",
                        "startOffsets": "31709,32097,32236,32283,32338,33220,33274,33326,33375,33436",
                        "endColumns": "39,42,46,54,44,53,51,48,60,49",
                        "endOffsets": "31744,32135,32278,32333,32378,33269,33321,33370,33431,33481"
                    }
                },
                {
                    "source": "C:\\Users\\DELL\\.gradle\\caches\\transforms-2\\files-2.1\\290377ef3f04af0b2bf13aa0b54ad202\\core-1.1.0\\res\\values\\values.xml",
                    "from": {
                        "startLines": "2,3,6,7,8,9,10,11,12,13,14,15,16,17,18,19,20,21,22,23,24,25,26,27,28,29,30,31,32,33,34,35,36,37,38,39,40,41,42,43,44,45,46,47,48,49,50,51,52,53,54,55,56,57,58,59,60,61,62,63,64,65,66,67,68,69,70,71,72,73,74,75,76,77,78,79,83,84,88,89,90,91,98,141,173,210",
                        "startColumns": "4,4,4,4,4,4,4,4,4,4,4,4,4,4,4,4,4,4,4,4,4,4,4,4,4,4,4,4,4,4,4,4,4,4,4,4,4,4,4,4,4,4,4,4,4,4,4,4,4,4,4,4,4,4,4,4,4,4,4,4,4,4,4,4,4,4,4,4,4,4,4,4,4,4,4,4,4,4,4,4,4,4,4,4,4,4",
                        "startOffsets": "55,124,319,389,457,529,599,660,734,807,868,929,991,1055,1117,1178,1246,1346,1406,1472,1545,1614,1671,1723,1785,1857,1933,1998,2057,2116,2176,2236,2296,2356,2416,2476,2536,2596,2656,2716,2775,2835,2895,2955,3015,3075,3135,3195,3255,3315,3375,3434,3494,3554,3613,3672,3731,3790,3849,3908,3943,3978,4033,4096,4151,4209,4266,4316,4377,4434,4468,4503,4538,4608,4679,4796,4997,5107,5308,5437,5509,5576,5874,8780,10845,12605",
                        "endLines": "2,3,6,7,8,9,10,11,12,13,14,15,16,17,18,19,20,21,22,23,24,25,26,27,28,29,30,31,32,33,34,35,36,37,38,39,40,41,42,43,44,45,46,47,48,49,50,51,52,53,54,55,56,57,58,59,60,61,62,63,64,65,66,67,68,69,70,71,72,73,74,75,76,77,78,82,83,87,88,89,90,97,140,172,209,216",
                        "endColumns": "68,62,69,67,71,69,60,73,72,60,60,61,63,61,60,67,99,59,65,72,68,56,51,61,71,75,64,58,58,59,59,59,59,59,59,59,59,59,59,58,59,59,59,59,59,59,59,59,59,59,58,59,59,58,58,58,58,58,58,34,34,54,62,54,57,56,49,60,56,33,34,34,69,70,116,12,109,12,128,71,66,24,24,24,24,24",
                        "endOffsets": "119,182,384,452,524,594,655,729,802,863,924,986,1050,1112,1173,1241,1341,1401,1467,1540,1609,1666,1718,1780,1852,1928,1993,2052,2111,2171,2231,2291,2351,2411,2471,2531,2591,2651,2711,2770,2830,2890,2950,3010,3070,3130,3190,3250,3310,3370,3429,3489,3549,3608,3667,3726,3785,3844,3903,3938,3973,4028,4091,4146,4204,4261,4311,4372,4429,4463,4498,4533,4603,4674,4791,4992,5102,5303,5432,5504,5571,5869,8775,10840,12600,12977"
                    },
                    "to": {
                        "startLines": "245,246,346,347,348,349,350,351,352,460,461,462,463,464,465,466,467,468,469,470,471,472,473,474,487,488,489,490,491,492,493,494,495,496,497,498,499,500,501,502,503,504,505,506,507,508,509,510,511,512,513,514,515,516,517,518,519,520,521,530,531,543,544,545,546,547,548,549,550,551,552,556,579,670,2382,2383,2388,2391,2396,2759,2760,3836,4046,4089,4122,4159",
                        "startColumns": "4,4,4,4,4,4,4,4,4,4,4,4,4,4,4,4,4,4,4,4,4,4,4,4,4,4,4,4,4,4,4,4,4,4,4,4,4,4,4,4,4,4,4,4,4,4,4,4,4,4,4,4,4,4,4,4,4,4,4,4,4,4,4,4,4,4,4,4,4,4,4,4,4,4,4,4,4,4,4,4,4,4,4,4,4,4",
                        "startOffsets": "13512,13581,20426,20496,20564,20636,20706,20767,20841,27738,27799,27860,27922,27986,28048,28109,28177,28277,28337,28403,28476,28545,28602,28654,29381,29453,29529,29594,29653,29712,29772,29832,29892,29952,30012,30072,30132,30192,30252,30312,30371,30431,30491,30551,30611,30671,30731,30791,30851,30911,30971,31030,31090,31150,31209,31268,31327,31386,31445,31907,31942,32517,32572,32635,32690,32748,32805,32855,32916,32973,33007,33185,34499,43130,157036,157153,157420,157713,157980,182382,182454,244168,262228,265134,267401,269161",
                        "endLines": "245,246,346,347,348,349,350,351,352,460,461,462,463,464,465,466,467,468,469,470,471,472,473,474,487,488,489,490,491,492,493,494,495,496,497,498,499,500,501,502,503,504,505,506,507,508,509,510,511,512,513,514,515,516,517,518,519,520,521,530,531,543,544,545,546,547,548,549,550,551,552,556,579,670,2382,2386,2388,2394,2396,2759,2760,3842,4088,4120,4158,4165",
                        "endColumns": "68,62,69,67,71,69,60,73,72,60,60,61,63,61,60,67,99,59,65,72,68,56,51,61,71,75,64,58,58,59,59,59,59,59,59,59,59,59,59,58,59,59,59,59,59,59,59,59,59,59,58,59,59,58,58,58,58,58,58,34,34,54,62,54,57,56,49,60,56,33,34,34,69,70,116,12,109,12,128,71,66,24,24,24,24,24",
                        "endOffsets": "13576,13639,20491,20559,20631,20701,20762,20836,20909,27794,27855,27917,27981,28043,28104,28172,28272,28332,28398,28471,28540,28597,28649,28711,29448,29524,29589,29648,29707,29767,29827,29887,29947,30007,30067,30127,30187,30247,30307,30366,30426,30486,30546,30606,30666,30726,30786,30846,30906,30966,31025,31085,31145,31204,31263,31322,31381,31440,31499,31937,31972,32567,32630,32685,32743,32800,32850,32911,32968,33002,33037,33215,34564,43196,157148,157349,157525,157909,158104,182449,182516,244461,265129,267194,269156,269533"
                    }
                },
                {
                    "source": "C:\\Users\\DELL\\AndroidStudioProjects\\Postie11\\app\\src\\main\\res\\values\\strings.xml",
                    "from": {
                        "startLines": "1,4",
                        "startColumns": "4,4",
                        "startOffsets": "17,127",
                        "endColumns": "47,69",
                        "endOffsets": "60,192"
                    },
                    "to": {
                        "startLines": "619,659",
                        "startColumns": "4,4",
                        "startOffsets": "37327,41824",
                        "endColumns": "47,69",
                        "endOffsets": "37370,41889"
                    }
                },
                {
                    "source": "C:\\Users\\DELL\\.gradle\\caches\\transforms-2\\files-2.1\\4e2dcb64655f459da3b0ba6a3a8b131a\\viewpager2-1.0.0\\res\\values\\values.xml",
                    "from": {
                        "startLines": "2",
                        "startColumns": "4",
                        "startOffsets": "55",
                        "endLines": "4",
                        "endColumns": "24",
                        "endOffsets": "160"
                    },
                    "to": {
                        "startLines": "4805",
                        "startColumns": "4",
                        "startOffsets": "306726",
                        "endLines": "4807",
                        "endColumns": "24",
                        "endOffsets": "306831"
                    }
                },
                {
                    "source": "C:\\Users\\DELL\\.gradle\\caches\\transforms-2\\files-2.1\\c2ecd1bc2ca1582550f1ff70e2797465\\media-1.0.0\\res\\values\\values.xml",
                    "from": {
                        "startLines": "2,5,6,7,8,10,11,12,13,14",
                        "startColumns": "4,4,4,4,4,4,4,4,4,4",
                        "startOffsets": "55,288,341,394,447,560,626,748,809,875",
                        "endColumns": "88,52,52,52,52,65,121,60,65,66",
                        "endOffsets": "139,336,389,442,495,621,743,804,870,937"
                    },
                    "to": {
                        "startLines": "247,475,476,477,478,2387,2389,2390,2395,2397",
                        "startColumns": "4,4,4,4,4,4,4,4,4,4",
                        "startOffsets": "13644,28716,28769,28822,28875,157354,157530,157652,157914,158109",
                        "endColumns": "88,52,52,52,52,65,121,60,65,66",
                        "endOffsets": "13728,28764,28817,28870,28923,157415,157647,157708,157975,158171"
                    }
                },
                {
                    "source": "C:\\Users\\DELL\\AndroidStudioProjects\\Postie11\\app\\src\\main\\res\\values\\styles.xml",
                    "from": {
                        "startLines": "3,14,24",
                        "startColumns": "4,4,4",
                        "startOffsets": "57,487,875",
                        "endLines": "11,22,32",
                        "endColumns": "12,12,12",
                        "endOffsets": "477,867,1304"
                    },
                    "to": {
                        "startLines": "680,2112,3038",
                        "startColumns": "4,4,4",
                        "startOffsets": "43920,136675,199350",
                        "endLines": "688,2120,3046",
                        "endColumns": "12,12,12",
                        "endOffsets": "44332,137047,199771"
                    }
                },
                {
                    "source": "C:\\Users\\DELL\\.gradle\\caches\\transforms-2\\files-2.1\\9ada9e59480a6739c9fc4544e5e5116b\\cardview-1.0.0\\res\\values\\values.xml",
                    "from": {
                        "startLines": "2,3,4,5,6,35,36,37,38,45,47,50,7",
                        "startColumns": "4,4,4,4,4,4,4,4,4,4,4,4,4",
                        "startOffsets": "55,107,168,230,292,2179,2238,2295,2349,2763,2827,2953,356",
                        "endLines": "2,3,4,5,6,35,36,37,44,46,49,52,34",
                        "endColumns": "51,60,61,61,63,58,56,53,12,12,12,12,24",
                        "endOffsets": "102,163,225,287,351,2233,2290,2344,2758,2822,2948,3076,2174"
                    },
                    "to": {
                        "startLines": "15,189,190,191,192,343,344,345,710,2104,2106,2109,3749",
                        "startColumns": "4,4,4,4,4,4,4,4,4,4,4,4,4",
                        "startOffsets": "734,9780,9841,9903,9965,20256,20315,20372,45788,136357,136421,136547,237928",
                        "endLines": "15,189,190,191,192,343,344,345,716,2105,2108,2111,3776",
                        "endColumns": "51,60,61,61,63,58,56,53,12,12,12,12,24",
                        "endOffsets": "781,9836,9898,9960,10024,20310,20367,20421,46197,136416,136542,136670,239746"
                    }
                },
                {
                    "source": "C:\\Users\\DELL\\.gradle\\caches\\transforms-2\\files-2.1\\4f3544d200097d1926e6df3e9bf8bd41\\material-1.0.0\\res\\values\\values.xml",
                    "from": {
                        "startLines": "2,3,4,5,6,7,8,9,10,11,12,13,14,15,16,17,18,19,20,21,22,23,24,25,26,27,28,29,30,31,32,33,34,35,36,37,38,39,40,41,42,43,44,45,46,47,48,49,50,51,52,53,54,218,219,220,221,222,223,224,225,226,227,228,229,230,231,232,233,234,235,236,237,238,239,240,241,242,243,244,245,246,247,248,249,250,251,252,253,254,255,256,257,258,259,260,261,262,263,264,265,266,267,268,269,270,271,272,273,274,275,276,277,278,279,280,281,282,283,284,285,286,287,288,289,290,291,292,293,294,295,296,297,298,299,300,301,302,303,304,305,306,307,308,309,310,311,312,313,314,315,316,317,318,319,320,321,322,323,324,325,326,327,328,329,330,331,332,333,334,335,336,337,338,339,340,341,345,346,347,352,353,357,363,367,368,369,370,381,382,383,387,393,397,398,399,400,430,450,496,526,546,566,612,616,620,634,675,683,693,694,695,696,697,700,701,704,707,708,711,715,720,728,736,745,753,757,765,773,781,789,797,806,815,823,832,835,837,842,844,849,853,857,858,863,864,865,866,867,868,870,871,876,877,878,879,880,881,882,884,888,892,896,900,901,902,903,904,905,906,907,908,911,915,918,922,930,937,946,950,965,973,976,985,990,1001,1009,1012,1021,1028,1029,1048,1051,1057,1060,1069,1072,1075,1078,1081,1084,1088,1091,1100,1103,1111,1116,1124,1129,1133,1134,1145,1152,1156,1160,1161,1165,1173,1177,1182,1187,55,56,57,76,82,92,96,97,98,141,149,150,158,159,160,161,167,168,169,170,171,172,173,174,175,198,217",
                        "startColumns": "4,4,4,4,4,4,4,4,4,4,4,4,4,4,4,4,4,4,4,4,4,4,4,4,4,4,4,4,4,4,4,4,4,4,4,4,4,4,4,4,4,4,4,4,4,4,4,4,4,4,4,4,4,4,4,4,4,4,4,4,4,4,4,4,4,4,4,4,4,4,4,4,4,4,4,4,4,4,4,4,4,4,4,4,4,4,4,4,4,4,4,4,4,4,4,4,4,4,4,4,4,4,4,4,4,4,4,4,4,4,4,4,4,4,4,4,4,4,4,4,4,4,4,4,4,4,4,4,4,4,4,4,4,4,4,4,4,4,4,4,4,4,4,4,4,4,4,4,4,4,4,4,4,4,4,4,4,4,4,4,4,4,4,4,4,4,4,4,4,4,4,4,4,4,4,4,4,4,4,4,4,4,4,4,4,4,4,4,4,4,4,4,4,4,4,4,4,4,4,4,4,4,4,4,4,4,4,4,4,4,4,4,4,4,4,4,4,4,4,4,4,4,4,4,4,4,4,4,4,4,4,4,4,4,4,4,4,4,4,4,4,4,4,4,4,4,4,4,4,4,4,4,4,4,4,4,4,4,4,4,4,4,4,4,4,4,4,4,4,4,4,4,4,4,4,4,4,4,4,4,4,4,4,4,4,4,4,4,4,4,4,4,4,4,4,4,4,4,4,4,4,4,4,4,4,4,4,4,4,4,4,4,4,4,4,4,4,4,4,4,4,4,4,4,4,4,4,4,4,4,4,4,4,4,4,4,4,4,4,4,4,4,4,4,4,4,4,4",
                        "startOffsets": "100,156,216,277,332,385,443,491,540,585,638,696,756,814,860,920,973,1019,1069,1116,1174,1232,1291,1351,1413,1475,1537,1599,1661,1723,1784,1846,1908,1961,2023,2097,2160,2228,2309,2373,2439,2509,2579,2649,2719,2786,2849,2914,2980,3033,3109,3175,3262,18372,18426,18505,18583,18656,18721,18784,18850,18921,18992,19054,19123,19189,19256,19323,19379,19430,19483,19535,19589,19660,19723,19782,19844,19903,19976,20043,20103,20166,20241,20313,20384,20440,20511,20568,20625,20691,20755,20826,20883,20936,20999,21051,21109,21176,21242,21308,21389,21464,21520,21573,21634,21692,21742,21791,21840,21889,21951,22003,22048,22129,22183,22236,22290,22341,22390,22441,22502,22563,22625,22675,22716,22766,22814,22876,22927,22976,23045,23106,23162,23233,23298,23367,23418,23481,23551,23620,23690,23752,23822,23892,23967,24026,24084,24146,24191,24234,24281,24326,24377,24425,24491,24553,24616,24688,24745,24802,24862,24920,24990,25047,25197,25328,25432,25519,25676,25833,25986,26067,26145,26446,26612,26767,26869,27146,27239,27346,27689,27796,28025,28434,28666,28766,28871,28990,29613,29760,29879,30114,30529,30767,30879,31000,31133,33276,34792,38088,40227,41755,43299,46591,46837,47096,47900,49660,50110,50825,50898,50985,51070,51169,51364,51456,51629,51791,51886,52055,52298,52591,53000,53414,53874,54292,54533,54963,55398,55808,56230,56640,57097,57551,57967,58433,58615,58683,59027,59107,59463,59613,59757,59841,60206,60304,60412,60510,60620,60736,60862,60958,61335,61445,61569,61707,61817,61939,62067,62205,62367,62583,62739,62943,63027,63131,63225,63339,63451,63575,63671,63751,63940,64146,64339,64549,64981,65402,65827,66024,66972,67493,67616,68253,68474,69289,69758,69941,70537,70997,71102,72363,72513,72930,73095,73775,73934,74096,74251,74447,74614,74836,74996,75373,75532,75860,76077,76652,77002,77251,77348,78054,78492,78733,78922,79056,79247,79884,80134,80437,80652,3338,3636,3892,4389,4823,5480,5823,7362,7710,9607,9929,10060,10766,10903,11055,11257,11962,12082,13231,13798,13927,14060,14220,14395,14537,16324,18162",
                        "endLines": "2,3,4,5,6,7,8,9,10,11,12,13,14,15,16,17,18,19,20,21,22,23,24,25,26,27,28,29,30,31,32,33,34,35,36,37,38,39,40,41,42,43,44,45,46,47,48,49,50,51,52,53,54,218,219,220,221,222,223,224,225,226,227,228,229,230,231,232,233,234,235,236,237,238,239,240,241,242,243,244,245,246,247,248,249,250,251,252,253,254,255,256,257,258,259,260,261,262,263,264,265,266,267,268,269,270,271,272,273,274,275,276,277,278,279,280,281,282,283,284,285,286,287,288,289,290,291,292,293,294,295,296,297,298,299,300,301,302,303,304,305,306,307,308,309,310,311,312,313,314,315,316,317,318,319,320,321,322,323,324,325,326,327,328,329,330,331,332,333,334,335,336,337,338,339,340,344,345,346,351,352,356,362,366,367,368,369,380,381,382,386,392,396,397,398,399,429,449,495,525,545,565,611,615,619,633,674,682,692,693,694,695,696,699,700,703,706,707,710,714,719,727,735,744,752,756,764,772,780,788,796,805,814,822,831,834,836,841,843,848,852,856,857,862,863,864,865,866,867,869,870,875,876,877,878,879,880,881,883,887,891,895,899,900,901,902,903,904,905,906,907,910,914,917,921,929,936,945,949,964,972,975,984,989,1000,1008,1011,1020,1027,1028,1047,1050,1056,1059,1068,1071,1074,1077,1080,1083,1087,1090,1099,1102,1110,1115,1123,1128,1132,1133,1144,1151,1155,1159,1160,1164,1172,1176,1181,1186,1195,55,56,75,81,91,95,96,97,140,148,149,157,158,159,160,166,167,168,169,170,171,172,173,174,197,216,217",
                        "endColumns": "55,59,60,54,52,57,47,48,44,52,57,59,57,45,59,52,45,49,46,57,57,58,59,61,61,61,61,61,61,60,61,61,52,61,73,62,67,80,63,65,69,69,69,69,66,62,64,65,52,75,65,86,75,53,78,77,72,64,62,65,70,70,61,68,65,66,66,55,50,52,51,53,70,62,58,61,58,72,66,59,62,74,71,70,55,70,56,56,65,63,70,56,52,62,51,57,66,65,65,80,74,55,52,60,57,49,48,48,48,61,51,44,80,53,52,53,50,48,50,60,60,61,49,40,49,47,61,50,48,68,60,55,70,64,68,50,62,69,68,69,61,69,69,74,58,57,61,44,42,46,44,50,47,65,61,62,71,56,56,59,57,69,56,149,130,103,86,156,156,152,80,77,300,165,154,101,10,92,106,10,106,10,10,10,99,104,118,10,146,118,10,10,10,111,120,132,10,10,10,10,10,10,10,10,10,10,10,10,10,72,86,84,98,10,91,10,10,94,10,10,10,10,10,10,10,10,10,10,10,10,10,10,10,10,10,10,10,10,10,10,10,10,83,10,97,107,97,109,115,10,95,10,109,123,137,109,121,127,10,10,10,10,10,83,103,93,113,111,123,95,79,10,10,10,10,10,10,10,10,10,10,10,10,10,10,10,10,10,10,104,10,10,10,10,10,10,10,10,10,10,10,10,10,10,10,10,10,10,10,96,10,10,10,10,133,10,10,10,10,10,10,297,255,90,243,367,188,1538,347,95,94,130,412,136,151,201,220,119,1148,566,128,132,159,174,141,125,457,209",
                        "endOffsets": "151,211,272,327,380,438,486,535,580,633,691,751,809,855,915,968,1014,1064,1111,1169,1227,1286,1346,1408,1470,1532,1594,1656,1718,1779,1841,1903,1956,2018,2092,2155,2223,2304,2368,2434,2504,2574,2644,2714,2781,2844,2909,2975,3028,3104,3170,3257,3333,18421,18500,18578,18651,18716,18779,18845,18916,18987,19049,19118,19184,19251,19318,19374,19425,19478,19530,19584,19655,19718,19777,19839,19898,19971,20038,20098,20161,20236,20308,20379,20435,20506,20563,20620,20686,20750,20821,20878,20931,20994,21046,21104,21171,21237,21303,21384,21459,21515,21568,21629,21687,21737,21786,21835,21884,21946,21998,22043,22124,22178,22231,22285,22336,22385,22436,22497,22558,22620,22670,22711,22761,22809,22871,22922,22971,23040,23101,23157,23228,23293,23362,23413,23476,23546,23615,23685,23747,23817,23887,23962,24021,24079,24141,24186,24229,24276,24321,24372,24420,24486,24548,24611,24683,24740,24797,24857,24915,24985,25042,25192,25323,25427,25514,25671,25828,25981,26062,26140,26441,26607,26762,26864,27141,27234,27341,27684,27791,28020,28429,28661,28761,28866,28985,29608,29755,29874,30109,30524,30762,30874,30995,31128,33271,34787,38083,40222,41750,43294,46586,46832,47091,47895,49655,50105,50820,50893,50980,51065,51164,51359,51451,51624,51786,51881,52050,52293,52586,52995,53409,53869,54287,54528,54958,55393,55803,56225,56635,57092,57546,57962,58428,58610,58678,59022,59102,59458,59608,59752,59836,60201,60299,60407,60505,60615,60731,60857,60953,61330,61440,61564,61702,61812,61934,62062,62200,62362,62578,62734,62938,63022,63126,63220,63334,63446,63570,63666,63746,63935,64141,64334,64544,64976,65397,65822,66019,66967,67488,67611,68248,68469,69284,69753,69936,70532,70992,71097,72358,72508,72925,73090,73770,73929,74091,74246,74442,74609,74831,74991,75368,75527,75855,76072,76647,76997,77246,77343,78049,78487,78728,78917,79051,79242,79879,80129,80432,80647,81228,3631,3887,4384,4818,5475,5818,7357,7705,9602,9924,10055,10761,10898,11050,11252,11957,12077,13226,13793,13922,14055,14215,14390,14532,16319,18157,18367"
                    },
                    "to": {
                        "startLines": "11,12,13,14,17,18,19,20,30,32,142,143,144,146,147,148,149,150,151,152,153,154,155,156,157,158,159,160,161,162,163,164,165,170,204,205,206,207,208,209,210,211,212,213,214,237,238,239,240,241,242,243,244,353,354,355,356,357,358,359,360,361,362,363,364,365,366,367,368,369,370,371,372,373,374,375,376,377,378,379,380,381,382,383,384,385,386,387,388,389,390,391,392,393,394,395,396,412,413,414,415,416,417,418,419,420,421,422,423,424,425,426,427,428,429,430,431,432,433,434,435,436,437,438,439,440,441,442,443,444,445,446,447,448,449,450,451,452,453,454,455,456,457,458,459,532,533,540,541,553,554,555,563,566,567,570,571,573,574,575,576,577,578,620,621,622,623,651,652,660,661,662,663,664,665,666,676,949,950,951,956,957,961,967,971,972,973,974,985,986,987,991,997,1001,1071,1072,1073,1103,1123,1169,1199,1219,1239,1285,1289,2031,2045,2086,2094,2246,2247,2248,2249,2398,2401,2402,2405,2408,2409,2412,2416,2421,2429,2437,2446,2454,2458,2466,2474,2482,2490,2498,2507,2516,2524,2533,2571,2573,2578,2580,2585,2589,2593,2594,2599,2600,2601,2602,2603,2604,2606,2607,2612,2613,2614,2615,2616,2617,2618,2620,2624,2628,2632,2643,2644,2645,2646,2647,2648,2649,2650,2651,2654,2658,2661,2761,2769,2776,2785,2789,2804,2812,2815,2824,2829,2840,2848,2851,2860,2867,2868,2887,2890,2896,2899,2908,2911,2914,2917,2920,2923,2927,2930,2939,2942,2950,2955,2963,2968,2972,2973,2984,2991,2995,2999,3000,3004,3012,3016,3021,3026,3219,3220,3221,3724,3730,3740,3777,3778,3785,3828,4017,4036,4044,4045,4121,4228,4234,4235,4420,4466,4467,4524,4525,4636,4637,4675,4694",
                        "startColumns": "4,4,4,4,4,4,4,4,4,4,4,4,4,4,4,4,4,4,4,4,4,4,4,4,4,4,4,4,4,4,4,4,4,4,4,4,4,4,4,4,4,4,4,4,4,4,4,4,4,4,4,4,4,4,4,4,4,4,4,4,4,4,4,4,4,4,4,4,4,4,4,4,4,4,4,4,4,4,4,4,4,4,4,4,4,4,4,4,4,4,4,4,4,4,4,4,4,4,4,4,4,4,4,4,4,4,4,4,4,4,4,4,4,4,4,4,4,4,4,4,4,4,4,4,4,4,4,4,4,4,4,4,4,4,4,4,4,4,4,4,4,4,4,4,4,4,4,4,4,4,4,4,4,4,4,4,4,4,4,4,4,4,4,4,4,4,4,4,4,4,4,4,4,4,4,4,4,4,4,4,4,4,4,4,4,4,4,4,4,4,4,4,4,4,4,4,4,4,4,4,4,4,4,4,4,4,4,4,4,4,4,4,4,4,4,4,4,4,4,4,4,4,4,4,4,4,4,4,4,4,4,4,4,4,4,4,4,4,4,4,4,4,4,4,4,4,4,4,4,4,4,4,4,4,4,4,4,4,4,4,4,4,4,4,4,4,4,4,4,4,4,4,4,4,4,4,4,4,4,4,4,4,4,4,4,4,4,4,4,4,4,4,4,4,4,4,4,4,4,4,4,4,4,4,4,4,4,4,4,4,4,4,4,4,4,4,4,4,4,4,4,4,4,4,4,4,4,4,4,4,4,4,4,4,4,4,4,4,4,4,4,4,4,4,4,4,4,4",
                        "startOffsets": "502,558,618,679,834,887,945,993,1444,1534,6714,6772,6832,6946,6992,7052,7105,7151,7201,7248,7306,7364,7423,7483,7545,7607,7669,7731,7793,7855,7916,7978,8040,8310,10844,10918,10981,11049,11130,11194,11260,11330,11400,11470,11540,12960,13023,13088,13154,13207,13283,13349,13436,20914,20968,21047,21125,21198,21263,21326,21392,21463,21534,21596,21665,21731,21798,21865,21921,21972,22025,22077,22131,22202,22265,22324,22386,22445,22518,22585,22645,22708,22783,22855,22926,22982,23053,23110,23167,23233,23297,23368,23425,23478,23541,23593,23651,24888,24954,25020,25101,25176,25232,25285,25346,25404,25454,25503,25552,25601,25663,25715,25760,25841,25895,25948,26002,26053,26102,26153,26214,26275,26337,26387,26428,26478,26526,26588,26639,26688,26757,26818,26874,26945,27010,27079,27130,27193,27263,27332,27402,27464,27534,27604,27679,31977,32035,32383,32428,33042,33089,33134,33518,33692,33758,33937,34000,34140,34197,34254,34314,34372,34442,37375,37525,37656,37760,40892,41049,41894,42047,42128,42206,42507,42673,42828,43643,61365,61458,61565,61908,62015,62244,62653,62885,62985,63090,63209,63832,63979,64098,64333,64748,64986,70257,70378,70511,72654,74170,77466,79605,81133,82677,85969,86215,132628,133432,135192,135642,146326,146399,146486,146571,158176,158371,158463,158636,158798,158893,159062,159305,159598,160007,160421,160881,161299,161540,161970,162405,162815,163237,163647,164104,164558,164974,165440,168206,168274,168618,168698,169054,169204,169348,169432,169797,169895,170003,170101,170211,170327,170453,170549,170926,171036,171160,171298,171408,171530,171658,171796,171958,172174,172330,173206,173290,173394,173488,173602,173714,173838,173934,174014,174203,174409,174602,182521,182953,183374,183799,183996,184944,185465,185588,186225,186446,187261,187730,187913,188509,188969,189074,190335,190485,190902,191067,191747,191906,192068,192223,192419,192586,192808,192968,193345,193504,193832,194049,194624,194974,195223,195320,196026,196464,196705,196894,197028,197219,197856,198106,198409,198624,209838,210136,210392,236234,236668,237325,239751,241290,241949,243846,260069,261233,261939,262076,267199,272592,273297,273417,283312,286249,286378,288978,289138,295715,295857,298245,300083",
                        "endLines": "11,12,13,14,17,18,19,20,30,32,142,143,144,146,147,148,149,150,151,152,153,154,155,156,157,158,159,160,161,162,163,164,165,170,204,205,206,207,208,209,210,211,212,213,214,237,238,239,240,241,242,243,244,353,354,355,356,357,358,359,360,361,362,363,364,365,366,367,368,369,370,371,372,373,374,375,376,377,378,379,380,381,382,383,384,385,386,387,388,389,390,391,392,393,394,395,396,412,413,414,415,416,417,418,419,420,421,422,423,424,425,426,427,428,429,430,431,432,433,434,435,436,437,438,439,440,441,442,443,444,445,446,447,448,449,450,451,452,453,454,455,456,457,458,459,532,533,540,541,553,554,555,563,566,567,570,571,573,574,575,576,577,578,620,621,622,623,651,652,660,661,662,663,664,665,666,679,949,950,955,956,960,966,970,971,972,973,984,985,986,990,996,1000,1001,1071,1072,1102,1122,1168,1198,1218,1238,1284,1288,1292,2044,2085,2093,2103,2246,2247,2248,2249,2400,2401,2404,2407,2408,2411,2415,2420,2428,2436,2445,2453,2457,2465,2473,2481,2489,2497,2506,2515,2523,2532,2535,2572,2577,2579,2584,2588,2592,2593,2598,2599,2600,2601,2602,2603,2605,2606,2611,2612,2613,2614,2615,2616,2617,2619,2623,2627,2631,2635,2643,2644,2645,2646,2647,2648,2649,2650,2653,2657,2660,2664,2768,2775,2784,2788,2803,2811,2814,2823,2828,2839,2847,2850,2859,2866,2867,2886,2889,2895,2898,2907,2910,2913,2916,2919,2922,2926,2929,2938,2941,2949,2954,2962,2967,2971,2972,2983,2990,2994,2998,2999,3003,3011,3015,3020,3025,3034,3219,3220,3239,3729,3739,3743,3777,3778,3827,3835,4017,4043,4044,4045,4121,4233,4234,4235,4420,4466,4467,4524,4525,4636,4659,4693,4694",
                        "endColumns": "55,59,60,54,52,57,47,48,44,52,57,59,57,45,59,52,45,49,46,57,57,58,59,61,61,61,61,61,61,60,61,61,52,61,73,62,67,80,63,65,69,69,69,69,66,62,64,65,52,75,65,86,75,53,78,77,72,64,62,65,70,70,61,68,65,66,66,55,50,52,51,53,70,62,58,61,58,72,66,59,62,74,71,70,55,70,56,56,65,63,70,56,52,62,51,57,66,65,65,80,74,55,52,60,57,49,48,48,48,61,51,44,80,53,52,53,50,48,50,60,60,61,49,40,49,47,61,50,48,68,60,55,70,64,68,50,62,69,68,69,61,69,69,74,58,57,61,44,42,46,44,50,47,65,61,62,71,56,56,59,57,69,56,149,130,103,86,156,156,152,80,77,300,165,154,101,10,92,106,10,106,10,10,10,99,104,118,10,146,118,10,10,10,111,120,132,10,10,10,10,10,10,10,10,10,10,10,10,10,72,86,84,98,10,91,10,10,94,10,10,10,10,10,10,10,10,10,10,10,10,10,10,10,10,10,10,10,10,10,10,10,10,83,10,97,107,97,109,115,10,95,10,109,123,137,109,121,127,10,10,10,10,10,83,103,93,113,111,123,95,79,10,10,10,10,10,10,10,10,10,10,10,10,10,10,10,10,10,10,104,10,10,10,10,10,10,10,10,10,10,10,10,10,10,10,10,10,10,10,96,10,10,10,10,133,10,10,10,10,10,10,297,255,90,243,367,188,1538,347,95,94,130,412,136,151,201,220,119,1148,566,128,132,159,174,141,125,457,209",
                        "endOffsets": "553,613,674,729,882,940,988,1037,1484,1582,6767,6827,6885,6987,7047,7100,7146,7196,7243,7301,7359,7418,7478,7540,7602,7664,7726,7788,7850,7911,7973,8035,8088,8367,10913,10976,11044,11125,11189,11255,11325,11395,11465,11535,11602,13018,13083,13149,13202,13278,13344,13431,13507,20963,21042,21120,21193,21258,21321,21387,21458,21529,21591,21660,21726,21793,21860,21916,21967,22020,22072,22126,22197,22260,22319,22381,22440,22513,22580,22640,22703,22778,22850,22921,22977,23048,23105,23162,23228,23292,23363,23420,23473,23536,23588,23646,23713,24949,25015,25096,25171,25227,25280,25341,25399,25449,25498,25547,25596,25658,25710,25755,25836,25890,25943,25997,26048,26097,26148,26209,26270,26332,26382,26423,26473,26521,26583,26634,26683,26752,26813,26869,26940,27005,27074,27125,27188,27258,27327,27397,27459,27529,27599,27674,27733,32030,32092,32423,32466,33084,33129,33180,33561,33753,33815,33995,34067,34192,34249,34309,34367,34437,34494,37520,37651,37755,37842,41044,41201,42042,42123,42201,42502,42668,42823,42925,43915,61453,61560,61903,62010,62239,62648,62880,62980,63085,63204,63827,63974,64093,64328,64743,64981,65093,70373,70506,72649,74165,77461,79600,81128,82672,85964,86210,86469,133427,135187,135637,136352,146394,146481,146566,146665,158366,158458,158631,158793,158888,159057,159300,159593,160002,160416,160876,161294,161535,161965,162400,162810,163232,163642,164099,164553,164969,165435,165617,168269,168613,168693,169049,169199,169343,169427,169792,169890,169998,170096,170206,170322,170448,170544,170921,171031,171155,171293,171403,171525,171653,171791,171953,172169,172325,172529,173285,173389,173483,173597,173709,173833,173929,174009,174198,174404,174597,174807,182948,183369,183794,183991,184939,185460,185583,186220,186441,187256,187725,187908,188504,188964,189069,190330,190480,190897,191062,191742,191901,192063,192218,192414,192581,192803,192963,193340,193499,193827,194044,194619,194969,195218,195315,196021,196459,196700,196889,197023,197214,197851,198101,198404,198619,199200,210131,210387,210884,236663,237320,237663,241285,241633,243841,244163,260195,261934,262071,262223,267396,273292,273412,274561,283874,286373,286506,289133,289308,295852,297639,300078,300288"
                    }
                },
                {
                    "source": "C:\\Users\\DELL\\.gradle\\caches\\transforms-2\\files-2.1\\3ca7664084ef6174ed0d76f6cd5121b0\\appcompat-1.0.2\\res\\values\\values.xml",
                    "from": {
                        "startLines": "2,3,4,5,6,7,8,9,10,11,12,13,14,15,16,17,18,19,20,21,22,23,24,25,26,27,28,29,30,31,32,33,34,35,36,37,38,39,40,41,42,43,44,45,46,47,48,49,50,51,52,53,54,55,56,57,58,59,60,61,62,63,64,65,66,67,68,1303,1304,1305,1306,1307,1308,1309,1310,1311,1312,1313,1314,1315,1316,1317,1318,1319,1320,1321,1322,1323,1324,1325,1326,1327,1328,1329,1330,1331,1332,1333,1334,1335,1336,1337,1338,1339,1340,1341,1342,1343,1344,1345,1346,1347,1348,1349,1350,1351,1352,1353,1354,1355,1356,1357,1358,1359,1360,1361,1362,1363,1364,1365,1366,1367,1368,1369,1370,1371,1372,1373,1374,1375,1376,1377,1378,1379,1380,1381,1382,1383,1384,1385,1386,1387,1388,1389,1390,1391,1392,1393,1394,1395,1396,1397,1398,1399,1400,1401,1402,1403,1404,1405,1406,1407,1408,1409,1410,1411,1412,1413,1414,1415,1416,1417,1418,1419,1420,1421,1422,1423,1424,1425,1426,1427,1428,1429,1430,1431,1432,1433,1434,1435,1436,1437,1438,1439,1440,1441,1442,1443,1444,1445,1446,1447,1448,1449,1450,1451,1452,1453,1461,1462,1466,1470,1474,1479,1485,1492,1496,1500,1505,1509,1513,1517,1521,1525,1529,1535,1539,1545,1549,1555,1559,1564,1568,1571,1575,1581,1585,1591,1595,1601,1604,1608,1612,1616,1620,1624,1625,1626,1627,1630,1633,1636,1639,1643,1644,1645,1646,1647,1650,1652,1654,1656,1661,1662,1666,1672,1676,1677,1679,1690,1691,1695,1701,1705,1706,1707,1711,1738,1742,1743,1747,1775,1943,1969,2138,2164,2195,2203,2209,2223,2245,2250,2255,2265,2274,2283,2287,2294,2302,2309,2310,2319,2322,2325,2329,2333,2337,2340,2341,2345,2349,2359,2364,2371,2377,2378,2381,2385,2390,2392,2394,2397,2400,2402,2406,2409,2416,2419,2422,2426,2428,2432,2434,2436,2438,2442,2450,2458,2470,2476,2485,2488,2499,2502,2507,2508,2513,2571,2630,2631,2641,2650,2651,2653,2657,2660,2663,2666,2669,2672,2675,2678,2682,2685,2688,2691,2695,2698,2702,2706,2707,2708,2709,2710,2711,2712,2713,2714,2715,2716,2717,2718,2719,2720,2721,2722,2723,2724,2725,2726,2728,2730,2731,2732,2733,2734,2735,2736,2737,2739,2740,2742,2743,2745,2747,2748,2750,2751,2752,2753,2754,2755,2757,2758,2759,2760,2761,2762,2764,2766,2768,2769,2770,2771,2772,2773,2774,2775,2776,2777,2778,2779,2780,2782,2783,2784,2785,2786,2787,2789,2793,2797,2798,2799,2800,2801,2802,2803,2804,2806,2808,2810,2812,2814,2815,2816,2817,2819,2821,2823,2824,2825,2826,2827,2828,2829,2830,2831,2832,2833,2834,2837,2838,2839,2840,2842,2844,2845,2847,2848,2850,2852,2854,2855,2856,2857,2858,2859,2860,2861,2862,2863,2864,2865,2867,2868,2869,2870,2872,2873,2874,2875,2876,2878,2880,2882,2884,2885,2886,2887,2888,2889,2890,2891,2892,2893,2894,2895,2896,2897,69,152,155,158,161,175,186,196,223,230,241,271,298,307,344,725,730,756,774,810,816,822,845,986,1006,1012,1016,1022,1059,1071,1098,1103,1169,1184,1249,1268,1294",
                        "startColumns": "4,4,4,4,4,4,4,4,4,4,4,4,4,4,4,4,4,4,4,4,4,4,4,4,4,4,4,4,4,4,4,4,4,4,4,4,4,4,4,4,4,4,4,4,4,4,4,4,4,4,4,4,4,4,4,4,4,4,4,4,4,4,4,4,4,4,4,4,4,4,4,4,4,4,4,4,4,4,4,4,4,4,4,4,4,4,4,4,4,4,4,4,4,4,4,4,4,4,4,4,4,4,4,4,4,4,4,4,4,4,4,4,4,4,4,4,4,4,4,4,4,4,4,4,4,4,4,4,4,4,4,4,4,4,4,4,4,4,4,4,4,4,4,4,4,4,4,4,4,4,4,4,4,4,4,4,4,4,4,4,4,4,4,4,4,4,4,4,4,4,4,4,4,4,4,4,4,4,4,4,4,4,4,4,4,4,4,4,4,4,4,4,4,4,4,4,4,4,4,4,4,4,4,4,4,4,4,4,4,4,4,4,4,4,4,4,4,4,4,4,4,4,4,4,4,4,4,4,4,4,4,4,4,4,4,4,4,4,4,4,4,4,4,4,4,4,4,4,4,4,4,4,4,4,4,4,4,4,4,4,4,4,4,4,4,4,4,4,4,4,4,4,4,4,4,4,4,4,4,4,4,4,4,4,4,4,4,4,4,4,4,4,4,4,4,4,4,4,4,4,4,4,4,4,4,4,4,4,4,4,4,4,4,4,4,4,4,4,4,4,4,4,4,4,4,4,4,4,4,4,4,4,4,4,4,4,4,4,4,4,4,4,4,4,4,4,4,4,4,4,4,4,4,4,4,4,4,4,4,4,4,4,4,4,4,4,4,4,4,4,4,4,4,4,4,4,4,4,4,4,4,4,4,4,4,4,4,4,4,4,4,4,4,4,4,4,4,4,4,4,4,4,4,4,4,4,4,4,4,4,4,4,4,4,4,4,4,4,4,4,4,4,4,4,4,4,4,4,4,4,4,4,4,4,4,4,4,4,4,4,4,4,4,4,4,4,4,4,4,4,4,4,4,4,4,4,4,4,4,4,4,4,4,4,4,4,4,4,4,4,4,4,4,4,4,4,4,4,4,4,4,4,4,4,4,4,4,4,4,4,4,4,4,4,4,4,4,4,4,4,4,4,4,4,4,4,4,4,4,4,4,4,4,4,4,4,4,4,4,4,4,4,4,4,4,4,4,4,4,4,4,4,4,4,4,4,4,4,4,4,4,4,4,4,4,4,4,4,4,4,4,4,4,4,4,4,4,4,4,4,4,4,4,4,4,4,4",
                        "startOffsets": "105,160,205,254,295,350,409,471,552,613,688,764,841,919,1004,1086,1162,1238,1315,1393,1499,1605,1684,1764,1821,1879,1953,2028,2093,2159,2219,2280,2352,2425,2492,2560,2619,2678,2737,2796,2855,2909,2963,3016,3070,3124,3178,3232,3306,3385,3458,3532,3603,3675,3747,3820,3877,3935,4008,4082,4156,4231,4303,4376,4446,4517,4577,70911,70980,71049,71119,71193,71269,71333,71410,71486,71563,71628,71697,71774,71849,71918,71986,72063,72129,72190,72287,72352,72421,72520,72591,72650,72708,72765,72824,72888,72959,73031,73103,73175,73247,73314,73382,73450,73509,73572,73636,73726,73817,73877,73943,74010,74076,74146,74210,74263,74376,74434,74497,74562,74627,74702,74775,74847,74896,74957,75018,75079,75141,75205,75269,75333,75398,75461,75521,75582,75648,75707,75767,75829,75900,75960,76028,76114,76201,76291,76378,76466,76548,76631,76721,76812,76864,76922,76967,77033,77097,77154,77211,77265,77322,77370,77419,77470,77504,77551,77600,77646,77678,77742,77804,77864,77921,77995,78065,78143,78197,78267,78352,78400,78446,78517,78595,78673,78745,78819,78893,78967,79047,79120,79189,79261,79338,79399,79462,79528,79592,79663,79726,79791,79855,79916,79977,80029,80102,80176,80245,80320,80394,80468,80609,80679,80732,80810,80900,80988,81084,81174,81756,81845,82092,82373,82625,82910,83303,83780,84002,84224,84500,84727,84957,85187,85417,85647,85874,86293,86519,86944,87174,87602,87821,88104,88312,88443,88670,89096,89321,89748,89969,90394,90514,90790,91091,91415,91706,92020,92157,92288,92393,92635,92802,93006,93214,93485,93597,93709,93814,93931,94145,94291,94431,94517,94865,94953,95199,95617,95866,95948,96046,96663,96763,97015,97439,97694,97788,97877,98114,100166,100408,100510,100763,102947,113668,115184,126004,127532,129289,129915,130335,131396,132661,132917,133153,133700,134194,134799,134997,135577,136141,136516,136634,137172,137329,137525,137798,138054,138224,138365,138429,138711,138997,139673,139937,140275,140628,140722,140908,141214,141476,141601,141728,141967,142178,142297,142490,142667,143122,143303,143425,143684,143797,143984,144086,144193,144322,144597,145105,145601,146478,146772,147342,147491,148223,148395,148731,148823,149101,153445,157932,157994,158624,159238,159329,159442,159671,159831,159983,160154,160320,160489,160656,160819,161062,161232,161405,161576,161850,162049,162254,162584,162668,162764,162860,162958,163058,163160,163262,163364,163466,163568,163668,163764,163876,164005,164128,164259,164390,164488,164602,164696,164836,164970,165066,165178,165278,165394,165490,165602,165702,165842,165978,166142,166272,166430,166580,166721,166865,167000,167112,167262,167390,167518,167654,167786,167916,168046,168158,168298,168444,168588,168726,168792,168882,168958,169062,169152,169254,169362,169470,169570,169650,169742,169840,169950,170028,170134,170226,170330,170440,170562,170725,170882,170962,171062,171152,171262,171356,171462,171554,171654,171766,171880,171996,172112,172206,172320,172432,172534,172654,172776,172858,172962,173082,173208,173306,173400,173488,173600,173716,173838,173950,174125,174241,174327,174419,174531,174655,174722,174848,174916,175044,175188,175316,175385,175480,175595,175708,175807,175916,176027,176138,176239,176344,176444,176574,176665,176788,176882,176994,177080,177184,177280,177368,177486,177590,177694,177820,177908,178016,178116,178206,178316,178400,178502,178586,178640,178704,178810,178920,179004,4638,9782,9900,10015,10147,10862,11554,12071,13718,14103,14700,16299,17832,18220,20527,40045,40305,41697,42730,44743,45005,45361,46191,52973,54107,54401,54624,54951,57001,57649,59282,59552,63403,64004,67813,69028,70437",
                        "endLines": "2,3,4,5,6,7,8,9,10,11,12,13,14,15,16,17,18,19,20,21,22,23,24,25,26,27,28,29,30,31,32,33,34,35,36,37,38,39,40,41,42,43,44,45,46,47,48,49,50,51,52,53,54,55,56,57,58,59,60,61,62,63,64,65,66,67,68,1303,1304,1305,1306,1307,1308,1309,1310,1311,1312,1313,1314,1315,1316,1317,1318,1319,1320,1321,1322,1323,1324,1325,1326,1327,1328,1329,1330,1331,1332,1333,1334,1335,1336,1337,1338,1339,1340,1341,1342,1343,1344,1345,1346,1347,1348,1349,1350,1351,1352,1353,1354,1355,1356,1357,1358,1359,1360,1361,1362,1363,1364,1365,1366,1367,1368,1369,1370,1371,1372,1373,1374,1375,1376,1377,1378,1379,1380,1381,1382,1383,1384,1385,1386,1387,1388,1389,1390,1391,1392,1393,1394,1395,1396,1397,1398,1399,1400,1401,1402,1403,1404,1405,1406,1407,1408,1409,1410,1411,1412,1413,1414,1415,1416,1417,1418,1419,1420,1421,1422,1423,1424,1425,1426,1427,1428,1429,1430,1431,1432,1433,1434,1435,1436,1437,1438,1439,1440,1441,1442,1443,1444,1445,1446,1447,1448,1449,1450,1451,1452,1460,1461,1465,1469,1473,1478,1484,1491,1495,1499,1504,1508,1512,1516,1520,1524,1528,1534,1538,1544,1548,1554,1558,1563,1567,1570,1574,1580,1584,1590,1594,1600,1603,1607,1611,1615,1619,1623,1624,1625,1626,1629,1632,1635,1638,1642,1643,1644,1645,1646,1649,1651,1653,1655,1660,1661,1665,1671,1675,1676,1678,1689,1690,1694,1700,1704,1705,1706,1710,1737,1741,1742,1746,1774,1942,1968,2137,2163,2194,2202,2208,2222,2244,2249,2254,2264,2273,2282,2286,2293,2301,2308,2309,2318,2321,2324,2328,2332,2336,2339,2340,2344,2348,2358,2363,2370,2376,2377,2380,2384,2389,2391,2393,2396,2399,2401,2405,2408,2415,2418,2421,2425,2427,2431,2433,2435,2437,2441,2449,2457,2469,2475,2484,2487,2498,2501,2506,2507,2512,2570,2629,2630,2640,2649,2650,2652,2656,2659,2662,2665,2668,2671,2674,2677,2681,2684,2687,2690,2694,2697,2701,2705,2706,2707,2708,2709,2710,2711,2712,2713,2714,2715,2716,2717,2718,2719,2720,2721,2722,2723,2724,2725,2727,2729,2730,2731,2732,2733,2734,2735,2736,2738,2739,2741,2742,2744,2746,2747,2749,2750,2751,2752,2753,2754,2756,2757,2758,2759,2760,2761,2763,2765,2767,2768,2769,2770,2771,2772,2773,2774,2775,2776,2777,2778,2779,2781,2782,2783,2784,2785,2786,2788,2792,2796,2797,2798,2799,2800,2801,2802,2803,2805,2807,2809,2811,2813,2814,2815,2816,2818,2820,2822,2823,2824,2825,2826,2827,2828,2829,2830,2831,2832,2833,2836,2837,2838,2839,2841,2843,2844,2846,2847,2849,2851,2853,2854,2855,2856,2857,2858,2859,2860,2861,2862,2863,2864,2866,2867,2868,2869,2871,2872,2873,2874,2875,2877,2879,2881,2883,2884,2885,2886,2887,2888,2889,2890,2891,2892,2893,2894,2895,2896,2897,151,154,157,160,174,185,195,222,229,240,270,297,306,343,724,729,755,773,809,815,821,844,985,1005,1011,1015,1021,1058,1070,1097,1102,1168,1183,1248,1267,1293,1302",
                        "endColumns": "54,44,48,40,54,58,61,80,60,74,75,76,77,84,81,75,75,76,77,105,105,78,79,56,57,73,74,64,65,59,60,71,72,66,67,58,58,58,58,58,53,53,52,53,53,53,53,73,78,72,73,70,71,71,72,56,57,72,73,73,74,71,72,69,70,59,60,68,68,69,73,75,63,76,75,76,64,68,76,74,68,67,76,65,60,96,64,68,98,70,58,57,56,58,63,70,71,71,71,71,66,67,67,58,62,63,89,90,59,65,66,65,69,63,52,112,57,62,64,64,74,72,71,48,60,60,60,61,63,63,63,64,62,59,60,65,58,59,61,70,59,67,85,86,89,86,87,81,82,89,90,51,57,44,65,63,56,56,53,56,47,48,50,33,46,48,45,31,63,61,59,56,73,69,77,53,69,84,47,45,70,77,77,71,73,73,73,79,72,68,71,76,60,62,65,63,70,62,64,63,60,60,51,72,73,68,74,73,73,140,69,52,77,89,87,95,89,12,88,12,12,12,12,12,12,12,12,12,12,12,12,12,12,12,12,12,12,12,12,12,12,12,12,12,12,12,12,12,12,12,12,12,12,12,12,136,130,104,12,12,12,12,12,111,111,104,116,12,12,12,12,12,87,12,12,12,81,12,12,99,12,12,12,93,88,12,12,12,101,12,12,12,12,12,12,12,12,12,12,12,12,12,12,12,12,12,12,12,12,117,12,12,12,12,12,12,12,63,12,12,12,12,12,12,93,12,12,12,12,12,12,12,12,12,12,12,12,12,12,12,12,12,12,12,12,12,12,12,12,12,12,12,12,12,91,12,12,12,61,12,12,90,12,12,12,12,12,12,12,12,12,12,12,12,12,12,12,12,12,83,95,95,97,99,101,101,101,101,101,99,95,111,128,122,130,130,97,113,93,12,12,95,111,99,115,95,111,99,12,135,12,129,12,12,140,12,134,111,149,127,127,12,131,129,129,111,139,12,12,12,65,89,75,103,89,101,107,107,99,79,91,97,12,77,105,91,103,109,12,12,12,79,99,89,109,93,105,91,12,12,12,12,12,93,113,111,12,12,12,81,103,119,125,97,93,87,111,115,121,111,12,115,85,91,12,12,66,12,67,12,12,12,68,94,114,112,98,108,110,110,100,104,99,12,90,122,93,12,85,103,95,87,12,12,12,12,87,107,99,89,109,83,101,83,53,63,105,109,83,119,24,24,24,24,24,24,24,24,24,24,24,24,24,24,24,24,24,24,24,24,24,24,24,24,24,24,24,24,24,24,24,24,24,24,24,24,24",
                        "endOffsets": "155,200,249,290,345,404,466,547,608,683,759,836,914,999,1081,1157,1233,1310,1388,1494,1600,1679,1759,1816,1874,1948,2023,2088,2154,2214,2275,2347,2420,2487,2555,2614,2673,2732,2791,2850,2904,2958,3011,3065,3119,3173,3227,3301,3380,3453,3527,3598,3670,3742,3815,3872,3930,4003,4077,4151,4226,4298,4371,4441,4512,4572,4633,70975,71044,71114,71188,71264,71328,71405,71481,71558,71623,71692,71769,71844,71913,71981,72058,72124,72185,72282,72347,72416,72515,72586,72645,72703,72760,72819,72883,72954,73026,73098,73170,73242,73309,73377,73445,73504,73567,73631,73721,73812,73872,73938,74005,74071,74141,74205,74258,74371,74429,74492,74557,74622,74697,74770,74842,74891,74952,75013,75074,75136,75200,75264,75328,75393,75456,75516,75577,75643,75702,75762,75824,75895,75955,76023,76109,76196,76286,76373,76461,76543,76626,76716,76807,76859,76917,76962,77028,77092,77149,77206,77260,77317,77365,77414,77465,77499,77546,77595,77641,77673,77737,77799,77859,77916,77990,78060,78138,78192,78262,78347,78395,78441,78512,78590,78668,78740,78814,78888,78962,79042,79115,79184,79256,79333,79394,79457,79523,79587,79658,79721,79786,79850,79911,79972,80024,80097,80171,80240,80315,80389,80463,80604,80674,80727,80805,80895,80983,81079,81169,81751,81840,82087,82368,82620,82905,83298,83775,83997,84219,84495,84722,84952,85182,85412,85642,85869,86288,86514,86939,87169,87597,87816,88099,88307,88438,88665,89091,89316,89743,89964,90389,90509,90785,91086,91410,91701,92015,92152,92283,92388,92630,92797,93001,93209,93480,93592,93704,93809,93926,94140,94286,94426,94512,94860,94948,95194,95612,95861,95943,96041,96658,96758,97010,97434,97689,97783,97872,98109,100161,100403,100505,100758,102942,113663,115179,125999,127527,129284,129910,130330,131391,132656,132912,133148,133695,134189,134794,134992,135572,136136,136511,136629,137167,137324,137520,137793,138049,138219,138360,138424,138706,138992,139668,139932,140270,140623,140717,140903,141209,141471,141596,141723,141962,142173,142292,142485,142662,143117,143298,143420,143679,143792,143979,144081,144188,144317,144592,145100,145596,146473,146767,147337,147486,148218,148390,148726,148818,149096,153440,157927,157989,158619,159233,159324,159437,159666,159826,159978,160149,160315,160484,160651,160814,161057,161227,161400,161571,161845,162044,162249,162579,162663,162759,162855,162953,163053,163155,163257,163359,163461,163563,163663,163759,163871,164000,164123,164254,164385,164483,164597,164691,164831,164965,165061,165173,165273,165389,165485,165597,165697,165837,165973,166137,166267,166425,166575,166716,166860,166995,167107,167257,167385,167513,167649,167781,167911,168041,168153,168293,168439,168583,168721,168787,168877,168953,169057,169147,169249,169357,169465,169565,169645,169737,169835,169945,170023,170129,170221,170325,170435,170557,170720,170877,170957,171057,171147,171257,171351,171457,171549,171649,171761,171875,171991,172107,172201,172315,172427,172529,172649,172771,172853,172957,173077,173203,173301,173395,173483,173595,173711,173833,173945,174120,174236,174322,174414,174526,174650,174717,174843,174911,175039,175183,175311,175380,175475,175590,175703,175802,175911,176022,176133,176234,176339,176439,176569,176660,176783,176877,176989,177075,177179,177275,177363,177481,177585,177689,177815,177903,178011,178111,178201,178311,178395,178497,178581,178635,178699,178805,178915,178999,179119,9777,9895,10010,10142,10857,11549,12066,13713,14098,14695,16294,17827,18215,20522,40040,40300,41692,42725,44738,45000,45356,46186,52968,54102,54396,54619,54946,56996,57644,59277,59547,63398,63999,67808,69023,70432,70906"
                    },
                    "to": {
                        "startLines": "25,31,33,166,167,168,169,171,172,173,174,175,176,177,178,179,180,181,182,183,184,185,186,187,188,215,216,217,218,219,220,221,222,223,224,225,226,227,228,229,230,231,232,233,234,235,236,248,249,250,251,252,253,254,255,256,257,258,259,260,261,262,263,264,265,266,267,268,269,270,271,272,273,274,275,276,277,278,279,280,281,282,283,284,285,286,287,288,289,290,291,292,293,294,295,296,297,298,299,300,301,302,303,304,305,306,307,308,309,310,311,312,313,314,315,316,317,318,319,320,321,322,323,324,325,326,327,328,329,330,331,332,333,334,335,336,337,338,339,340,341,342,397,398,402,403,404,405,406,407,408,479,480,481,482,483,484,485,486,522,523,524,525,528,535,536,542,562,564,565,568,569,580,581,582,583,584,585,586,587,588,589,590,591,592,593,594,595,596,597,598,599,600,601,602,603,604,605,606,607,608,609,610,611,612,613,614,615,616,617,618,669,671,672,673,674,675,689,697,698,702,706,717,722,728,735,739,743,748,752,756,760,764,768,772,778,782,788,792,798,802,807,811,814,818,824,828,834,838,844,847,851,855,859,863,867,868,869,870,873,876,879,882,886,887,888,889,890,893,895,897,899,904,905,909,915,919,920,922,933,934,938,944,948,1002,1003,1007,1034,1038,1039,1043,1293,1461,1487,1656,1682,1713,1721,1727,1741,1763,1768,1773,1783,1792,1801,1805,1812,1820,1827,1828,1837,1840,1843,1847,1851,1855,1858,1859,1863,1867,1877,1882,1889,1895,1896,1899,1903,1908,1910,1912,1915,1918,1920,1924,1927,1934,1937,1940,1944,1946,1950,1952,1954,1956,1960,1968,1976,1988,1994,2003,2006,2017,2020,2025,2026,2129,2187,2250,2251,2261,2270,2271,2273,2277,2280,2283,2286,2289,2292,2295,2298,2302,2305,2308,2311,2315,2318,2322,2326,2327,2328,2329,2330,2331,2332,2333,2334,2335,2336,2337,2338,2339,2340,2341,2342,2343,2344,2345,2346,2348,2350,2351,2352,2353,2354,2355,2356,2357,2359,2360,2362,2363,2365,2367,2368,2370,2371,2372,2373,2374,2375,2377,2378,2379,2380,2381,2536,2538,2540,2542,2543,2544,2545,2546,2547,2548,2549,2550,2551,2552,2553,2554,2556,2557,2558,2559,2560,2561,2563,2567,2636,2637,2638,2639,2640,2641,2642,2665,2667,2669,2671,2673,2675,2676,2677,2678,2680,2682,2684,2685,2686,2687,2688,2689,2690,2691,2692,2693,2694,2695,2698,2699,2700,2701,2703,2705,2706,2708,2709,2711,2713,2715,2716,2717,2718,2719,2720,2721,2722,2723,2724,2725,2726,2728,2729,2730,2731,2733,2734,2735,2736,2737,2739,2741,2743,2745,2746,2747,2748,2749,2750,2751,2752,2753,2754,2755,2756,2757,2758,3047,3130,3133,3136,3139,3153,3164,3174,3201,3208,3240,3270,3297,3306,3343,3744,3843,4018,4167,4203,4209,4236,4259,4400,4421,4427,4431,4468,4526,4538,4565,4570,4660,4695,4760,4779,4808",
                        "startColumns": "4,4,4,4,4,4,4,4,4,4,4,4,4,4,4,4,4,4,4,4,4,4,4,4,4,4,4,4,4,4,4,4,4,4,4,4,4,4,4,4,4,4,4,4,4,4,4,4,4,4,4,4,4,4,4,4,4,4,4,4,4,4,4,4,4,4,4,4,4,4,4,4,4,4,4,4,4,4,4,4,4,4,4,4,4,4,4,4,4,4,4,4,4,4,4,4,4,4,4,4,4,4,4,4,4,4,4,4,4,4,4,4,4,4,4,4,4,4,4,4,4,4,4,4,4,4,4,4,4,4,4,4,4,4,4,4,4,4,4,4,4,4,4,4,4,4,4,4,4,4,4,4,4,4,4,4,4,4,4,4,4,4,4,4,4,4,4,4,4,4,4,4,4,4,4,4,4,4,4,4,4,4,4,4,4,4,4,4,4,4,4,4,4,4,4,4,4,4,4,4,4,4,4,4,4,4,4,4,4,4,4,4,4,4,4,4,4,4,4,4,4,4,4,4,4,4,4,4,4,4,4,4,4,4,4,4,4,4,4,4,4,4,4,4,4,4,4,4,4,4,4,4,4,4,4,4,4,4,4,4,4,4,4,4,4,4,4,4,4,4,4,4,4,4,4,4,4,4,4,4,4,4,4,4,4,4,4,4,4,4,4,4,4,4,4,4,4,4,4,4,4,4,4,4,4,4,4,4,4,4,4,4,4,4,4,4,4,4,4,4,4,4,4,4,4,4,4,4,4,4,4,4,4,4,4,4,4,4,4,4,4,4,4,4,4,4,4,4,4,4,4,4,4,4,4,4,4,4,4,4,4,4,4,4,4,4,4,4,4,4,4,4,4,4,4,4,4,4,4,4,4,4,4,4,4,4,4,4,4,4,4,4,4,4,4,4,4,4,4,4,4,4,4,4,4,4,4,4,4,4,4,4,4,4,4,4,4,4,4,4,4,4,4,4,4,4,4,4,4,4,4,4,4,4,4,4,4,4,4,4,4,4,4,4,4,4,4,4,4,4,4,4,4,4,4,4,4,4,4,4,4,4,4,4,4,4,4,4,4,4,4,4,4,4,4,4,4,4,4,4,4,4,4,4,4,4,4,4,4,4,4,4,4,4,4,4,4,4,4,4,4,4,4,4,4,4,4,4,4,4,4,4,4,4,4,4,4,4,4,4,4,4,4,4,4,4,4,4,4,4,4,4,4,4,4,4,4,4,4,4,4,4,4,4,4,4,4,4,4,4,4,4,4,4,4,4,4,4,4,4,4,4,4,4,4,4,4",
                        "startOffsets": "1262,1489,1587,8093,8134,8189,8248,8372,8453,8514,8589,8665,8742,8820,8905,8987,9063,9139,9216,9294,9400,9506,9585,9665,9722,11607,11681,11756,11821,11887,11947,12008,12080,12153,12220,12288,12347,12406,12465,12524,12583,12637,12691,12744,12798,12852,12906,13733,13807,13886,13959,14033,14104,14176,14248,14321,14378,14436,14509,14583,14657,14732,14804,14877,14947,15018,15078,15139,15208,15277,15347,15421,15497,15561,15638,15714,15791,15856,15925,16002,16077,16146,16214,16291,16357,16418,16515,16580,16649,16748,16819,16878,16936,16993,17052,17116,17187,17259,17331,17403,17475,17542,17610,17678,17737,17800,17864,17954,18045,18105,18171,18238,18304,18374,18438,18491,18604,18662,18725,18790,18855,18930,19003,19075,19124,19185,19246,19307,19369,19433,19497,19561,19626,19689,19749,19810,19876,19935,19995,20057,20128,20188,23718,23804,24054,24144,24231,24319,24401,24484,24574,28928,28980,29038,29083,29149,29213,29270,29327,31504,31561,31609,31658,31807,32140,32187,32471,33486,33566,33630,33820,33880,34569,34643,34713,34791,34845,34915,35000,35048,35094,35165,35243,35321,35393,35467,35541,35615,35695,35768,35837,35909,35986,36047,36110,36176,36240,36311,36374,36439,36503,36564,36625,36677,36750,36824,36893,36968,37042,37116,37257,43077,43201,43279,43369,43457,43553,44337,44919,45008,45255,45536,46202,46487,46880,47357,47579,47801,48077,48304,48534,48764,48994,49224,49451,49870,50096,50521,50751,51179,51398,51681,51889,52020,52247,52673,52898,53325,53546,53971,54091,54367,54668,54992,55283,55597,55734,55865,55970,56212,56379,56583,56791,57062,57174,57286,57391,57508,57722,57868,58008,58094,58442,58530,58776,59194,59443,59525,59623,60240,60340,60592,61016,61271,65098,65187,65424,67476,67718,67820,68073,86474,97195,98711,109531,111059,112816,113442,113862,114923,116188,116444,116680,117227,117721,118326,118524,119104,119668,120043,120161,120699,120856,121052,121325,121581,121751,121892,121956,122238,122524,123200,123464,123802,124155,124249,124435,124741,125003,125128,125255,125494,125705,125824,126017,126194,126649,126830,126952,127211,127324,127511,127613,127720,127849,128124,128632,129128,130005,130299,130869,131018,131750,131922,132258,132350,137495,141839,146670,146732,147362,147976,148067,148180,148409,148569,148721,148892,149058,149227,149394,149557,149800,149970,150143,150314,150588,150787,150992,151322,151406,151502,151598,151696,151796,151898,152000,152102,152204,152306,152406,152502,152614,152743,152866,152997,153128,153226,153340,153434,153574,153708,153804,153916,154016,154132,154228,154340,154440,154580,154716,154880,155010,155168,155318,155459,155603,155738,155850,156000,156128,156256,156392,156524,156654,156784,156896,165622,165768,165912,166050,166116,166206,166282,166386,166476,166578,166686,166794,166894,166974,167066,167164,167274,167352,167458,167550,167654,167764,167886,168049,172534,172614,172714,172804,172914,173008,173114,174812,174912,175024,175138,175254,175370,175464,175578,175690,175792,175912,176034,176116,176220,176340,176466,176564,176658,176746,176858,176974,177096,177208,177383,177499,177585,177677,177789,177913,177980,178106,178174,178302,178446,178574,178643,178738,178853,178966,179065,179174,179285,179396,179497,179602,179702,179832,179923,180046,180140,180252,180338,180442,180538,180626,180744,180848,180952,181078,181166,181274,181374,181464,181574,181658,181760,181844,181898,181962,182068,182178,182262,199776,204920,205038,205153,205285,206000,206692,207209,208856,209241,210889,212488,214021,214409,216716,237668,244466,260200,269646,271659,271921,274566,275396,282178,283879,284173,284396,286511,289313,289961,291594,291864,297644,300293,304102,305317,306836",
                        "endLines": "25,31,33,166,167,168,169,171,172,173,174,175,176,177,178,179,180,181,182,183,184,185,186,187,188,215,216,217,218,219,220,221,222,223,224,225,226,227,228,229,230,231,232,233,234,235,236,248,249,250,251,252,253,254,255,256,257,258,259,260,261,262,263,264,265,266,267,268,269,270,271,272,273,274,275,276,277,278,279,280,281,282,283,284,285,286,287,288,289,290,291,292,293,294,295,296,297,298,299,300,301,302,303,304,305,306,307,308,309,310,311,312,313,314,315,316,317,318,319,320,321,322,323,324,325,326,327,328,329,330,331,332,333,334,335,336,337,338,339,340,341,342,397,398,402,403,404,405,406,407,408,479,480,481,482,483,484,485,486,522,523,524,525,528,535,536,542,562,564,565,568,569,580,581,582,583,584,585,586,587,588,589,590,591,592,593,594,595,596,597,598,599,600,601,602,603,604,605,606,607,608,609,610,611,612,613,614,615,616,617,618,669,671,672,673,674,675,696,697,701,705,709,721,727,734,738,742,747,751,755,759,763,767,771,777,781,787,791,797,801,806,810,813,817,823,827,833,837,843,846,850,854,858,862,866,867,868,869,872,875,878,881,885,886,887,888,889,892,894,896,898,903,904,908,914,918,919,921,932,933,937,943,947,948,1002,1006,1033,1037,1038,1042,1070,1460,1486,1655,1681,1712,1720,1726,1740,1762,1767,1772,1782,1791,1800,1804,1811,1819,1826,1827,1836,1839,1842,1846,1850,1854,1857,1858,1862,1866,1876,1881,1888,1894,1895,1898,1902,1907,1909,1911,1914,1917,1919,1923,1926,1933,1936,1939,1943,1945,1949,1951,1953,1955,1959,1967,1975,1987,1993,2002,2005,2016,2019,2024,2025,2030,2186,2245,2250,2260,2269,2270,2272,2276,2279,2282,2285,2288,2291,2294,2297,2301,2304,2307,2310,2314,2317,2321,2325,2326,2327,2328,2329,2330,2331,2332,2333,2334,2335,2336,2337,2338,2339,2340,2341,2342,2343,2344,2345,2347,2349,2350,2351,2352,2353,2354,2355,2356,2358,2359,2361,2362,2364,2366,2367,2369,2370,2371,2372,2373,2374,2376,2377,2378,2379,2380,2381,2537,2539,2541,2542,2543,2544,2545,2546,2547,2548,2549,2550,2551,2552,2553,2555,2556,2557,2558,2559,2560,2562,2566,2570,2636,2637,2638,2639,2640,2641,2642,2666,2668,2670,2672,2674,2675,2676,2677,2679,2681,2683,2684,2685,2686,2687,2688,2689,2690,2691,2692,2693,2694,2697,2698,2699,2700,2702,2704,2705,2707,2708,2710,2712,2714,2715,2716,2717,2718,2719,2720,2721,2722,2723,2724,2725,2727,2728,2729,2730,2732,2733,2734,2735,2736,2738,2740,2742,2744,2745,2746,2747,2748,2749,2750,2751,2752,2753,2754,2755,2756,2757,2758,3129,3132,3135,3138,3152,3163,3173,3200,3207,3218,3269,3296,3305,3342,3723,3748,3868,4035,4202,4208,4214,4258,4399,4419,4426,4430,4436,4504,4537,4564,4569,4635,4674,4759,4778,4804,4816",
                        "endColumns": "54,44,48,40,54,58,61,80,60,74,75,76,77,84,81,75,75,76,77,105,105,78,79,56,57,73,74,64,65,59,60,71,72,66,67,58,58,58,58,58,53,53,52,53,53,53,53,73,78,72,73,70,71,71,72,56,57,72,73,73,74,71,72,69,70,59,60,68,68,69,73,75,63,76,75,76,64,68,76,74,68,67,76,65,60,96,64,68,98,70,58,57,56,58,63,70,71,71,71,71,66,67,67,58,62,63,89,90,59,65,66,65,69,63,52,112,57,62,64,64,74,72,71,48,60,60,60,61,63,63,63,64,62,59,60,65,58,59,61,70,59,67,85,86,89,86,87,81,82,89,90,51,57,44,65,63,56,56,53,56,47,48,50,33,46,48,45,31,63,61,59,56,73,69,77,53,69,84,47,45,70,77,77,71,73,73,73,79,72,68,71,76,60,62,65,63,70,62,64,63,60,60,51,72,73,68,74,73,73,140,69,52,77,89,87,95,89,12,88,12,12,12,12,12,12,12,12,12,12,12,12,12,12,12,12,12,12,12,12,12,12,12,12,12,12,12,12,12,12,12,12,12,12,12,12,136,130,104,12,12,12,12,12,111,111,104,116,12,12,12,12,12,87,12,12,12,81,12,12,99,12,12,12,93,88,12,12,12,101,12,12,12,12,12,12,12,12,12,12,12,12,12,12,12,12,12,12,12,12,117,12,12,12,12,12,12,12,63,12,12,12,12,12,12,93,12,12,12,12,12,12,12,12,12,12,12,12,12,12,12,12,12,12,12,12,12,12,12,12,12,12,12,12,12,91,12,12,12,61,12,12,90,12,12,12,12,12,12,12,12,12,12,12,12,12,12,12,12,12,83,95,95,97,99,101,101,101,101,101,99,95,111,128,122,130,130,97,113,93,12,12,95,111,99,115,95,111,99,12,135,12,129,12,12,140,12,134,111,149,127,127,12,131,129,129,111,139,12,12,12,65,89,75,103,89,101,107,107,99,79,91,97,12,77,105,91,103,109,12,12,12,79,99,89,109,93,105,91,12,12,12,12,12,93,113,111,12,12,12,81,103,119,125,97,93,87,111,115,121,111,12,115,85,91,12,12,66,12,67,12,12,12,68,94,114,112,98,108,110,110,100,104,99,12,90,122,93,12,85,103,95,87,12,12,12,12,87,107,99,89,109,83,101,83,53,63,105,109,83,119,24,24,24,24,24,24,24,24,24,24,24,24,24,24,24,24,24,24,24,24,24,24,24,24,24,24,24,24,24,24,24,24,24,24,24,24,24",
                        "endOffsets": "1312,1529,1631,8129,8184,8243,8305,8448,8509,8584,8660,8737,8815,8900,8982,9058,9134,9211,9289,9395,9501,9580,9660,9717,9775,11676,11751,11816,11882,11942,12003,12075,12148,12215,12283,12342,12401,12460,12519,12578,12632,12686,12739,12793,12847,12901,12955,13802,13881,13954,14028,14099,14171,14243,14316,14373,14431,14504,14578,14652,14727,14799,14872,14942,15013,15073,15134,15203,15272,15342,15416,15492,15556,15633,15709,15786,15851,15920,15997,16072,16141,16209,16286,16352,16413,16510,16575,16644,16743,16814,16873,16931,16988,17047,17111,17182,17254,17326,17398,17470,17537,17605,17673,17732,17795,17859,17949,18040,18100,18166,18233,18299,18369,18433,18486,18599,18657,18720,18785,18850,18925,18998,19070,19119,19180,19241,19302,19364,19428,19492,19556,19621,19684,19744,19805,19871,19930,19990,20052,20123,20183,20251,23799,23886,24139,24226,24314,24396,24479,24569,24660,28975,29033,29078,29144,29208,29265,29322,29376,31556,31604,31653,31704,31836,32182,32231,32512,33513,33625,33687,33875,33932,34638,34708,34786,34840,34910,34995,35043,35089,35160,35238,35316,35388,35462,35536,35610,35690,35763,35832,35904,35981,36042,36105,36171,36235,36306,36369,36434,36498,36559,36620,36672,36745,36819,36888,36963,37037,37111,37252,37322,43125,43274,43364,43452,43548,43638,44914,45003,45250,45531,45783,46482,46875,47352,47574,47796,48072,48299,48529,48759,48989,49219,49446,49865,50091,50516,50746,51174,51393,51676,51884,52015,52242,52668,52893,53320,53541,53966,54086,54362,54663,54987,55278,55592,55729,55860,55965,56207,56374,56578,56786,57057,57169,57281,57386,57503,57717,57863,58003,58089,58437,58525,58771,59189,59438,59520,59618,60235,60335,60587,61011,61266,61360,65182,65419,67471,67713,67815,68068,70252,97190,98706,109526,111054,112811,113437,113857,114918,116183,116439,116675,117222,117716,118321,118519,119099,119663,120038,120156,120694,120851,121047,121320,121576,121746,121887,121951,122233,122519,123195,123459,123797,124150,124244,124430,124736,124998,125123,125250,125489,125700,125819,126012,126189,126644,126825,126947,127206,127319,127506,127608,127715,127844,128119,128627,129123,130000,130294,130864,131013,131745,131917,132253,132345,132623,141834,146321,146727,147357,147971,148062,148175,148404,148564,148716,148887,149053,149222,149389,149552,149795,149965,150138,150309,150583,150782,150987,151317,151401,151497,151593,151691,151791,151893,151995,152097,152199,152301,152401,152497,152609,152738,152861,152992,153123,153221,153335,153429,153569,153703,153799,153911,154011,154127,154223,154335,154435,154575,154711,154875,155005,155163,155313,155454,155598,155733,155845,155995,156123,156251,156387,156519,156649,156779,156891,157031,165763,165907,166045,166111,166201,166277,166381,166471,166573,166681,166789,166889,166969,167061,167159,167269,167347,167453,167545,167649,167759,167881,168044,168201,172609,172709,172799,172909,173003,173109,173201,174907,175019,175133,175249,175365,175459,175573,175685,175787,175907,176029,176111,176215,176335,176461,176559,176653,176741,176853,176969,177091,177203,177378,177494,177580,177672,177784,177908,177975,178101,178169,178297,178441,178569,178638,178733,178848,178961,179060,179169,179280,179391,179492,179597,179697,179827,179918,180041,180135,180247,180333,180437,180533,180621,180739,180843,180947,181073,181161,181269,181369,181459,181569,181653,181755,181839,181893,181957,182063,182173,182257,182377,204915,205033,205148,205280,205995,206687,207204,208851,209236,209833,212483,214016,214404,216711,236229,237923,245853,261228,271654,271916,272272,275391,282173,283307,284168,284391,284718,288556,289956,291589,291859,295710,298240,304097,305312,306721,307305"
                    }
                },
                {
                    "source": "C:\\Users\\DELL\\.gradle\\caches\\transforms-2\\files-2.1\\186ea041bf90cfd1698e007f3ea9bff3\\constraintlayout-1.1.3\\res\\values\\values.xml",
                    "from": {
                        "startLines": "2,3,11,12,13,14,15,19,20,21,22,25,26,29,32,33,34,35,36,39,42,43,44,45,50,53,56,57,58,63,64,65,68,71,72,75,78,81,84,85,88,91,92,97,98,103,106,109,110,111,112,113,114,115,116,117,118,127,128,129,130",
                        "startColumns": "4,4,4,4,4,4,4,4,4,4,4,4,4,4,4,4,4,4,4,4,4,4,4,4,4,4,4,4,4,4,4,4,4,4,4,4,4,4,4,4,4,4,4,4,4,4,4,4,4,4,4,4,4,4,4,4,4,4,4,4,4",
                        "startOffsets": "55,116,407,455,507,568,614,741,802,862,932,1065,1133,1262,1388,1450,1515,1583,1650,1773,1898,1965,2030,2095,2276,2397,2518,2584,2651,2861,2930,2996,3121,3247,3314,3440,3567,3692,3819,3884,4010,4133,4198,4406,4473,4653,4773,4893,4958,5020,5082,5144,5203,5263,5324,5385,5444,5819,8395,8527,11791",
                        "endLines": "2,10,11,12,13,14,18,19,20,21,24,25,28,31,32,33,34,35,38,41,42,43,44,49,52,55,56,57,62,63,64,67,70,71,74,77,80,83,84,87,90,91,96,97,102,105,108,109,110,111,112,113,114,115,116,117,126,127,128,129,130",
                        "endColumns": "60,11,47,51,60,45,11,60,59,69,11,67,11,11,61,64,67,66,11,11,66,64,64,11,11,11,65,66,11,68,65,11,11,66,11,11,11,11,64,11,11,64,11,66,11,11,11,64,61,61,61,58,59,60,60,58,11,2575,131,3263,107",
                        "endOffsets": "111,402,450,502,563,609,736,797,857,927,1060,1128,1257,1383,1445,1510,1578,1645,1768,1893,1960,2025,2090,2271,2392,2513,2579,2646,2856,2925,2991,3116,3242,3309,3435,3562,3687,3814,3879,4005,4128,4193,4401,4468,4648,4768,4888,4953,5015,5077,5139,5198,5258,5319,5380,5439,5814,8390,8522,11786,11894"
                    },
                    "to": {
                        "startLines": "2,3,16,21,22,23,26,34,35,36,37,40,41,44,47,48,49,50,51,54,57,58,59,60,65,68,71,72,73,78,79,80,83,86,87,90,93,96,99,100,103,106,107,112,113,118,121,124,125,126,127,128,129,130,131,132,133,3869,3870,3871,4166",
                        "startColumns": "4,4,4,4,4,4,4,4,4,4,4,4,4,4,4,4,4,4,4,4,4,4,4,4,4,4,4,4,4,4,4,4,4,4,4,4,4,4,4,4,4,4,4,4,4,4,4,4,4,4,4,4,4,4,4,4,4,4,4,4,4",
                        "startOffsets": "150,211,786,1042,1094,1155,1317,1636,1697,1757,1827,1960,2028,2157,2283,2345,2410,2478,2545,2668,2793,2860,2925,2990,3171,3292,3413,3479,3546,3756,3825,3891,4016,4142,4209,4335,4462,4587,4714,4779,4905,5028,5093,5301,5368,5548,5668,5788,5853,5915,5977,6039,6098,6158,6219,6280,6339,245858,248434,248566,269538",
                        "endLines": "2,10,16,21,22,23,29,34,35,36,39,40,43,46,47,48,49,50,53,56,57,58,59,64,67,70,71,72,77,78,79,82,85,86,89,92,95,98,99,102,105,106,111,112,117,120,123,124,125,126,127,128,129,130,131,132,141,3869,3870,3871,4166",
                        "endColumns": "60,11,47,51,60,45,11,60,59,69,11,67,11,11,61,64,67,66,11,11,66,64,64,11,11,11,65,66,11,68,65,11,11,66,11,11,11,11,64,11,11,64,11,66,11,11,11,64,61,61,61,58,59,60,60,58,11,2575,131,3263,107",
                        "endOffsets": "206,497,829,1089,1150,1196,1439,1692,1752,1822,1955,2023,2152,2278,2340,2405,2473,2540,2663,2788,2855,2920,2985,3166,3287,3408,3474,3541,3751,3820,3886,4011,4137,4204,4330,4457,4582,4709,4774,4900,5023,5088,5296,5363,5543,5663,5783,5848,5910,5972,6034,6093,6153,6214,6275,6334,6709,248429,248561,251825,269641"
                    }
                },
                {
                    "source": "C:\\Users\\DELL\\.gradle\\caches\\transforms-2\\files-2.1\\c4cce9e4b135e91b23e472ce13b797bf\\dexter-6.0.2\\res\\values\\values.xml",
                    "from": {
                        "startLines": "3",
                        "startColumns": "4",
                        "startOffsets": "99",
                        "endLines": "10",
                        "endColumns": "10",
                        "endOffsets": "537"
                    },
                    "to": {
                        "startLines": "2121",
                        "startColumns": "4",
                        "startOffsets": "137052",
                        "endLines": "2128",
                        "endColumns": "10",
                        "endOffsets": "137490"
                    }
                },
                {
                    "source": "C:\\Users\\DELL\\.gradle\\caches\\transforms-2\\files-2.1\\a963193221eb0286e753774bd7d2ff46\\recyclerview-1.1.0\\res\\values\\values.xml",
                    "from": {
                        "startLines": "2,3,4,5,6,7,8,9,10",
                        "startColumns": "4,4,4,4,4,4,4,4,4",
                        "startOffsets": "55,111,170,218,274,349,425,497,563",
                        "endLines": "2,3,4,5,6,7,8,9,38",
                        "endColumns": "55,58,47,55,74,75,71,65,24",
                        "endOffsets": "106,165,213,269,344,420,492,558,2084"
                    },
                    "to": {
                        "startLines": "145,399,400,401,409,410,411,529,4437",
                        "startColumns": "4,4,4,4,4,4,4,4,4",
                        "startOffsets": "6890,23891,23950,23998,24665,24740,24816,31841,284723",
                        "endLines": "145,399,400,401,409,410,411,529,4465",
                        "endColumns": "55,58,47,55,74,75,71,65,24",
                        "endOffsets": "6941,23945,23993,24049,24735,24811,24883,31902,286244"
                    }
                },
                {
                    "source": "C:\\Users\\DELL\\AndroidStudioProjects\\Postie11\\app\\src\\main\\res\\values\\colors.xml",
                    "from": {
                        "startLines": "4,2,3",
                        "startColumns": "4,4,4",
                        "startOffsets": "157,57,105",
                        "endColumns": "45,46,50",
                        "endOffsets": "198,99,151"
                    },
                    "to": {
                        "startLines": "193,194,195",
                        "startColumns": "4,4,4",
                        "startOffsets": "10029,10075,10122",
                        "endColumns": "45,46,50",
                        "endOffsets": "10070,10117,10168"
                    }
                },
                {
                    "source": "C:\\Users\\DELL\\AndroidStudioProjects\\Postie11\\app\\build\\generated\\res\\google-services\\debug\\values\\values.xml",
                    "from": {
                        "startLines": "2,3,4,5,6,7,8,9",
                        "startColumns": "4,4,4,4,4,4,4,4",
                        "startOffsets": "55,199,306,388,492,601,721,817",
                        "endColumns": "143,106,81,103,108,119,95,72",
                        "endOffsets": "194,301,383,487,596,716,812,885"
                    },
                    "to": {
                        "startLines": "650,653,654,655,656,657,658,668",
                        "startColumns": "4,4,4,4,4,4,4,4",
                        "startOffsets": "40748,41206,41313,41395,41499,41608,41728,43004",
                        "endColumns": "143,106,81,103,108,119,95,72",
                        "endOffsets": "40887,41308,41390,41494,41603,41723,41819,43072"
                    }
                },
                {
                    "source": "C:\\Users\\DELL\\.gradle\\caches\\transforms-2\\files-2.1\\474a111dca4edf4f4d4eb27557217693\\jetified-play-services-basement-17.0.0\\res\\values\\values.xml",
                    "from": {
                        "startLines": "4,7",
                        "startColumns": "0,0",
                        "startOffsets": "238,401",
                        "endColumns": "63,166",
                        "endOffsets": "301,567"
                    },
                    "to": {
                        "startLines": "572,632",
                        "startColumns": "4,4",
                        "startOffsets": "34072,38887",
                        "endColumns": "67,166",
                        "endOffsets": "34135,39049"
                    }
                },
                {
                    "source": "C:\\Users\\DELL\\.gradle\\caches\\transforms-2\\files-2.1\\cff2a38e78742c5afae0bc9773045ce5\\circleimageview-3.1.0\\res\\values\\values.xml",
                    "from": {
                        "startLines": "2",
                        "startColumns": "4",
                        "startOffsets": "55",
                        "endLines": "7",
                        "endColumns": "24",
                        "endOffsets": "361"
                    },
                    "to": {
                        "startLines": "3779",
                        "startColumns": "4",
                        "startOffsets": "241638",
                        "endLines": "3784",
                        "endColumns": "24",
                        "endOffsets": "241944"
                    }
                },
                {
                    "source": "C:\\Users\\DELL\\.gradle\\caches\\transforms-2\\files-2.1\\4d67033ccf8e0678872f48072867854a\\coordinatorlayout-1.0.0\\res\\values\\values.xml",
                    "from": {
                        "startLines": "2,102,3,13",
                        "startColumns": "4,4,4,4",
                        "startOffsets": "55,5935,116,724",
                        "endLines": "2,104,12,101",
                        "endColumns": "60,12,24,24",
                        "endOffsets": "111,6075,719,5930"
                    },
                    "to": {
                        "startLines": "24,3035,3872,3882",
                        "startColumns": "4,4,4,4",
                        "startOffsets": "1201,199205,251830,252438",
                        "endLines": "24,3037,3881,3970",
                        "endColumns": "60,12,24,24",
                        "endOffsets": "1257,199345,252433,257644"
                    }
                }
            ]
        }
    ]
}